yolosplitter.py
yolosplitter-0.5.0.0.dist-info/METADATA
yolosplitter-0.5.0.0.dist-info/WHEEL
yolosplitter-0.5.0.0.dist-info/top_level.txt
yolosplitter-0.5.0.0.dist-info/RECORD
