Metadata-Version: 2.1
Name: yolosplitter
Version: 0.5.0.0
Summary: Tool to Create,Modify YOLO dataset and much more...
Home-page: https://github.com/sandeshkharat87/yolo-splitter
Author: wpnx
Keywords: yolo splitter,split datasets,yolo split,yolos split dataset,yolo,yolosplitter,yolo-splitter
Classifier: Programming Language :: Python :: 3
Classifier: License :: OSI Approved :: MIT License
Classifier: Operating System :: OS Independent
Requires-Python: >=3.6
Requires-Dist: pandas
Requires-Dist: tqdm
Requires-Dist: PyYAML
